docxreviews2txt/__init__.py
docxreviews2txt/__main__.py
docxreviews2txt/docxreviews2txt.py
docxreviews2txt/version.py
docxreviews2txt-0.4.6.dist-info/METADATA
docxreviews2txt-0.4.6.dist-info/WHEEL
docxreviews2txt-0.4.6.dist-info/entry_points.txt
docxreviews2txt-0.4.6.dist-info/top_level.txt
docxreviews2txt-0.4.6.dist-info/RECORD
