Metadata-Version: 2.1
Name: docxreviews2txt
Version: 0.4.6
Summary: Command line tool to extract review changes from a docx file as plain text
Author-email: Alan Guedes <alanlivio@outlook.com>
License: MIT
Keywords: docx,docx reviews
Classifier: Development Status :: 1 - Planning
Classifier: Environment :: Console
Classifier: Operating System :: Microsoft :: Windows
Classifier: Intended Audience :: Science/Research
Classifier: License :: OSI Approved :: MIT License
Classifier: Operating System :: OS Independent
Classifier: Programming Language :: Python :: 3
Requires-Python: >=3.7
Requires-Dist: python-docx >=1.1.2
